Metadata-Version: 2.1
Name: stbi-py
Version: 0.0.1
Summary: Python wrapper for stb_image.
Home-page: https://github.com/Aermoss/stbiPy
Author: Yusuf Rençber
Author-email: aermoss.0@gmail.com
License: MIT
License-File: LICENSE
